gemma/__init__.py
gemma/layers.py
gemma/layers_test.py
gemma/modules.py
gemma/modules_test.py
gemma/params.py
gemma/positional_embeddings.py
gemma/positional_embeddings_test.py
gemma/sampler.py
gemma/sampler_test.py
gemma/transformer.py
gemma/transformer_test.py
gemma_llm-1.0.0.dist-info/LICENSE
gemma_llm-1.0.0.dist-info/METADATA
gemma_llm-1.0.0.dist-info/WHEEL
gemma_llm-1.0.0.dist-info/RECORD
