Metadata-Version: 2.1
Name: gemma-llm
Version: 1.0.0
Summary: Open weights large language model (LLM) from Google DeepMind.
License: Apache-2.0
Author: Alek Andreev
Author-email: alekandreev@google.com
Requires-Python: >=3.10
Classifier: License :: OSI Approved :: Apache Software License
Classifier: Programming Language :: Python :: 3
Classifier: Programming Language :: Python :: 3.10
Classifier: Programming Language :: Python :: 3.11
Classifier: Programming Language :: Python :: 3.12
Provides-Extra: test
Requires-Dist: absl-py (>=2.1.0,<3.0.0)
Requires-Dist: flax (>=0.7.5,<0.8.0)
Requires-Dist: pytest (>=8.0.0,<9.0.0) ; extra == "test"
Requires-Dist: sentencepiece (>=0.1.99,<0.2.0)
